{
  "langCode": "pl",
  "version": 39,
  "data": {
    "nav": {
      "start": "Start",
      "offers": "Oferty",
      "account": "Konto",
      "employees": "Pracownicy"
    },
    "pwa": {
      "install": "Zainstaluj na ekranie głównym",
      "success": "Aplikacja została pomyślnie zainstalowana",
      "iosGuide": "Aby zainstalować aplikację na iPhonie, wykonaj poniższe kroki:",
      "iosStep1": "Naciśnij przycisk Udostępnij w Safari",
      "iosStep2": "Przewiń w dół i wybierz \"Dodaj do ekranu początkowego\"",
      "iosStep3": "Naciśnij \"Dodaj\" w prawym górnym rogu"
    },
    "chat": {
      "chats": "Czaty",
      "noChats": "Brak dostępnych czatów",
      "chatMenu": "Menu czatu",
      "joinedAt": "Dołączono: {{date}}",
      "openChat": "Otwórz czat",
      "blockUser": "Zablokuj użytkownika",
      "cleanChat": "Wyczyść czat",
      "deleteChat": "Usuń czat",
      "noMessages": "Brak wiadomości",
      "blockedByMe": "Zablokowane przez Ciebie",
      "typeMessage": "Pisz wiadomość...",
      "blockedByOther": "Zablokowane przez ",
      "blockUserConfirm": "Czy na pewno chcesz zablokować tego użytkownika? Nie będziesz mógł wysyłać ani odbierać od niego wiadomości.",
      "blockUserSuccess": "Użytkownik został pomyślnie zablokowany",
      "cleanChatConfirm": "Czy na pewno chcesz wyczyścić historię czatu? Tej akcji nie można cofnąć.",
      "cleanChatSuccess": "Historia czatu została pomyślnie wyczyszczona",
      "deleteChatConfirm": "Czy na pewno chcesz usunąć ten czat? Tej akcji nie można cofnąć.",
      "deleteChatSuccess": "Czat został pomyślnie usunięty",
      "unblockUserConfirm": "Czy na pewno chcesz odblokować tego użytkownika? Będziesz mógł ponownie wysyłać i odbierać od niego wiadomości.",
      "unblockUserSuccess": "Użytkownik został pomyślnie odblokowany"
    },
    "lang": {
      "select": "Wybierz język",
      "language": "Język",
      "changedTo": "Język zmieniony na {{lang}}",
      "notDefined": "Język nie został zdefiniowany"
    },
    "user": {
      "lastSeen": "Ostatnio widziany",
      "error": {
        "notFound": "Nie znaleziono użytkownika",
        "invalidRole": "Nieprawidłowa rola",
        "cannotDelete": "Nie można usunąć użytkownika",
        "missingRoles": "Brak ról",
        "userInitError": "Błąd podczas inicjalizacji kontekstu użytkownika"
      }
    },
    "error": {
      "missingUserId": "Brak ID użytkownika",
      "settingsUpdate": "Nie udało się zaktualizować ustawień",
      "avatarUploadFailed": "Nie udało się przesłać avatara",
      "imageProcessingFailed": "Błąd podczas przetwarzania obrazu",
      "imageRemoveFailed": "Błąd podczas usuwania obrazu"
    },
    "offer": {
      "add": "Dodaj ofertę",
      "workLocation": "Lokalizacja",
      "form": {
        "title": "Formularz oferty pracy",
        "success": "Oferta została pomyślnie utworzona",
        "STEP_ONE": {
          "label": "Krok 1",
          "title": "Podstawowe informacje"
        },
        "STEP_TWO": {
          "info": "*Podanie orientacyjnej lokalizacji jest wymagane do działania wyszukiwarki i ułatwia innym znalezienie Twojej oferty.",
          "label": "Krok 2",
          "title": "Lokalizacja"
        },
        "STEP_FOUR": {
          "label": "Krok 4",
          "title": "Szczegóły"
        },
        "STEP_THREE": {
          "label": "Krok 3",
          "title": "Opis i wynagrodzenie"
        },
        "validation": {
          "notFound": "Nie znaleziono oferty.",
          "createError": "Błąd podczas tworzenia oferty, spróbuj ponownie później.",
          "formInvalid": "Formularz jest nieprawidłowy, sprawdź wszystkie pola.",
          "currencyRequired": "Waluta jest wymagana.",
          "atLeastOneSalaryRequired": "Wymagane jest podanie wynagrodzenia (miesięczne lub godzinowe)."
        },
        "successUpdate": "Oferta została pomyślnie zaktualizowana"
      },
      "likes": "Polubienia",
      "views": "Wyświetlenia",
      "salary": "Stawka godzinowa od",
      "search": "Szukaj ofert",
      "created": "Dodano",
      "filters": {
        "countries": "Kraje",
        "categories": "Kategorie",
        "communicationLanguages": "Języki komunikacji"
      },
      "currency": "Waluta",
      "noOffers": "Nie ma jeszcze żadnych ofert...",
      "dateRange": "Data rozpoczęcia",
      "offerMenu": "Menu oferty",
      "editButton": "Edytuj ofertę",
      "likeButton": "Polub ofertę",
      "management": "Zarządzanie ofertami",
      "offersList": "Lista ofert",
      "description": "Krótki opis oferty",
      "displayName": "Tytuł",
      "myListTitle": "Moje oferty",
      "searchTitle": "Oferty",
      "workCountry": "Kraj pracy",
      "deleteButton": "Usuń ofertę",
      "removeButton": "Usuń ofertę",
      "statusActive": "Aktywna",
      "unlikeButton": "Usuń polubienie oferty",
      "workCategory": "Kategoria",
      "activateButton": "Aktywuj ofertę",
      "offerViewTitle": "Szczegóły oferty",
      "statusInactive": "Nieaktywna",
      "likeRemoveToast": "Usunąłeś polubienie",
      "deactivateButton": "Dezaktywuj ofertę",
      "likeSuccessToast": "Polubiłeś ofertę",
      "languagesRequired": "Wymagane języki",
      "cannotLikeOwnOffer": "Nie możesz polubić własnej oferty",
      "deleteSuccessToast": "Oferta została pomyślnie usunięta",
      "languagesNiceToHave": "Mile widziane języki",
      "activationErrorToast": "Błąd podczas zmiany statusu aktywacji oferty",
      "deleteConfirmMessage": "Czy na pewno chcesz usunąć tę ofertę? Tej akcji nie można cofnąć.",
      "activationSuccessToast": "Oferta została pomyślnie aktywowana",
      "deactivationSuccessToast": "Oferta została pomyślnie dezaktywowana"
    },
    "theme": {
      "dark": "Ciemny",
      "light": "Jasny",
      "title": "Motyw",
      "select": "Wybierz motyw",
      "changedTo": "Motyw zmieniony na {{theme}}"
    },
    "common": {
      "h1": "Witamy w FRAT",
      "h2": "Platforma rekrutacyjna dla wysokościowych / pracowników dostępu linowego (rope-access)",
      "of": "z",
      "ok": "OK",
      "to": "do",
      "day": "dzień",
      "end": "Koniec",
      "sww": "Coś poszło nie tak, spróbuj ponownie później.",
      "back": "Wstecz",
      "edit": "Edytuj",
      "from": "Od",
      "hour": "godzina",
      "next": "Dalej",
      "page": "Strona",
      "save": "Zapisz",
      "year": "rok",
      "close": "Zamknij",
      "items": "elementów",
      "month": "miesiąc",
      "reset": "Reset",
      "start": "Początek",
      "cancel": "Anuluj",
      "search": "Szukaj",
      "submit": "Zatwierdź",
      "confirm": "Potwierdź",
      "filters": "Filtry",
      "options": "Opcje",
      "anywhere": "Gdziekolwiek",
      "distance": "Odległość",
      "language": "Język",
      "previous": "Wstecz",
      "settings": "Ustawienia",
      "noResults": "Brak wyników ;( ",
      "endOfResults": "Brak więcej wyników do wyświetlenia.",
      "yes": "Tak",
      "no": "Nie",
      "networkError": "Błąd sieci"
    },
    "header": {
      "home": "Strona główna",
      "admin": "Panel admina",
      "signUp": "Rejestracja",
      "profile": "Profil"
    },
    "others": {
      "lessThan": "< {{value}} {{unit}}",
      "availableAnytime": "Dostępny od zaraz",
      "availableFrom": "Dostępny od",
      "fetchLocationError": "Nie można znaleźć lokalizacji.",
      "availableAnytimeShort": "Od zaraz",
      "call": "Zadzwoń",
      "away": "stąd",
      "languages": "Języki"
    },
    "report": {
      "send": "Wyślij",
      "title": "Co możemy zrobić lepiej?",
      "sending": "Wysyłanie...",
      "thankYouMsg": "Doceniamy Twój głos i wykorzystamy go, aby ulepszyć naszą platformę.",
      "contactLabel": "Email - jeśli chcesz otrzymać odpowiedź",
      "errorRequired": "Wpisz swoją opinię.",
      "feedbackLabel": "Twoja opinia",
      "thankYouTitle": "Dziękujemy za Twoją opinię!",
      "feedbackPopupTitle": "Czy to już na pewno wszystko?"
    },
    "signin": {
      "pin": "PIN z Telegrama",
      "email": "Email",
      "title": "Logowanie",
      "logout": "Wyloguj się",
      "submit": "Zaloguj się",
      "openBot": "Otwórz bota Telegram",
      "signout": "Wylogowano!",
      "success": "Zalogowano pomyślnie!",
      "password": "Hasło",
      "noAccount": "Nie masz konta?",
      "signingIn": "Logowanie...",
      "signUpForm": "Formularz rejestracji przez email",
      "orSignInWith": " - Lub zaloguj się przez - ",
      "forgotPassword": "Nie pamiętasz hasła?",
      "googleProvider": "Zaloguj przez Google",
      "alreadyHaveAccount": "Masz już konto?",
      "forgotPasswordTitle": "Resetowanie hasła",
      "invalidOrExpiredPin": "PIN nieprawidłowy lub wygasł. Spróbuj ponownie.",
      "forgotPasswordSuccess": "Jeśli email istnieje, wysłano link do resetu hasła."
    },
    "signup": {
      "email": "Email",
      "title": "Rejestracja",
      "submit": "Załóż konto",
      "password": "Hasło",
      "registering": "Rejestracja...",
      "repeatEmail": "Powtórz email",
      "successTitle": "Rejestracja zakończona sukcesem",
      "errorRequired": "Wszystkie pola są wymagane.",
      "repeatPassword": "Powtórz hasło",
      "successMessage": "Sprawdź swój email, aby zweryfikować konto.",
      "errorEmailMatch": "Emaile się nie zgadzają.",
      "errorPasswordMatch": "Hasła się nie zgadzają.",
      "verificationEmailSent": "Email weryfikacyjny został wysłany. Sprawdź swoją skrzynkę.",
      "resendVerificationEmail": "Wyślij ponownie email weryfikacyjny",
      "emailVerificationMessage": "Musisz zweryfikować swój adres email, aby uzyskać dostęp do wszystkich funkcji.",
      "emailVerificationRequired": "Wymagana jest weryfikacja email."
    },
    "account": {
      "offers": "Oferty",
      "account": "Konto",
      "friends": "Znajomi",
      "showProfile": "Pokaż profil",
      "deleteAccountFailed": "Nie udało się usunąć konta",
      "showEmployeeProfile": "Pokaż profil pracownika",
      "createEmployeeProfile": "Utwórz profil pracownika",
      "deleteAccountConfirmTitle": "Usuń konto",
      "deleteAccountSuccessToast": "Konto zostało pomyślnie usunięte",
      "deleteAccountConfirmMessage": "Czy na pewno chcesz usunąć swoje konto? Tej akcji nie można cofnąć."
    },
    "cookies": {
      "title": "Informacja o plikach cookie",
      "accept": "Akceptuję",
      "description": "Używamy niezbędnych plików cookie, aby zapewnić prawidłowe działanie strony. Te pliki umożliwiają podstawowe funkcje, takie jak nawigacja, uwierzytelnianie i bezpieczeństwo."
    },
    "friends": {
      "accept": "Zaakceptuj",
      "cancel": "Anuluj",
      "friend": "Znajomy",
      "invite": "Zaproś do znajomych",
      "reject": "Odrzuć zaproszenie",
      "remove": "Usuń znajomego",
      "search": "Szukaj znajomych",
      "invited": "Zaproszony przez Ciebie",
      "noFriends": "Nie masz jeszcze żadnych znajomych. Wyszukaj i dodaj kilku!",
      "endOfResults": "Brak więcej wyników do wyświetlenia.",
      "removeFailed": "Nie udało się usunąć znajomego",
      "acceptedToast": "Zaproszenie zaakceptowane",
      "rejectedToast": "Zaproszenie odrzucone",
      "removeConfirm": "Czy na pewno chcesz usunąć tego znajomego?",
      "removeSuccess": "Znajomy został pomyślnie usunięty",
      "invitationSent": "Zaproszenie wysłane",
      "cancelInvitation": "Anuluj zaproszenie",
      "invitationReceived": "Otrzymane zaproszenie",
      "inviteReceivedToast": "Użytkownik {{name}} wysłał Ci zaproszenie.",
      "invitationNotification": "Masz nowe zaproszenie",
      "cancelInvitationConfirm": "Czy na pewno chcesz anulować to zaproszenie?",
      "cancelInvitationSuccess": "Zaproszenie zostało odrzucone"
    },
    "profile": {
      "add": "Dodaj profil",
      "tile": "Twój profil"
    },
    "success": {
      "avatarUploaded": "Avatar został przesłany"
    },
    "authError": {
      "userDisabled": "Konto zablokowane",
      "userNotFound": "Nieprawidłowy email lub hasło",
      "wrongPassword": "Nieprawidłowy email lub hasło",
      "sessionExpired": "Sesja wygasła, zaloguj się ponownie.",
      "tooManyRequests": "Zbyt wiele prób. Spróbuj ponownie później.",
      "invalidCredential": "Nieprawidłowy email lub hasło",
      "passwordResetNotError": "Błąd podczas wysyłania emaila do resetu hasła.",
      "passwordResetNotAvailable": "Reset hasła nie jest dostępny dla tego konta."
    },
    "callendar": {
      "at": "o godzinie",
      "month": {
        "0": "Styczeń",
        "1": "Luty",
        "2": "Marzec",
        "3": "Kwiecień",
        "4": "Maj",
        "5": "Czerwiec",
        "6": "Lipiec",
        "7": "Sierpień",
        "8": "Wrzesień",
        "9": "Październik",
        "10": "Listopad",
        "11": "Grudzień"
      },
      "today": "Dzisiaj",
      "control": {
        "anytime": "Kiedykolwiek",
        "rangeEndLabel": "do",
        "rangeStartLabel": "od",
        "rangeEndPlaceholder": "Wybierz datę zakończenia",
        "rangeStartPlaceholder": "Wybierz datę rozpoczęcia"
      },
      "duration": {
        "month": "miesiąc",
        "title": "Czas trwania",
        "months": "miesięcy",
        "months2": "miesiące",
        "selectLabel": "Wybierz liczbę miesięcy"
      },
      "tomorrow": "Jutro",
      "yesterday": "Wczoraj",
      "monthShort": {
        "0": "Sty",
        "1": "Lut",
        "2": "Mar",
        "3": "Kwi",
        "4": "Maj",
        "5": "Cze",
        "6": "Lip",
        "7": "Sie",
        "8": "Wrz",
        "9": "Paź",
        "10": "Lis",
        "11": "Gru"
      },
      "dayOfWeekFull": {
        "0": "Niedziela",
        "1": "Poniedziałek",
        "2": "Wtorek",
        "3": "Środa",
        "4": "Czwartek",
        "5": "Piątek",
        "6": "Sobota"
      },
      "dayOfWeekLetter": {
        "0": "N",
        "1": "P",
        "2": "W",
        "3": "Ś",
        "4": "C",
        "5": "P",
        "6": "S"
      },
      "dayOfWeekThreeLetter": {
        "0": "Nie",
        "1": "Pon",
        "2": "Wto",
        "3": "Śro",
        "4": "Czw",
        "5": "Pią",
        "6": "Sob"
      }
    },
    "cloudinary": {
      "missingConfig": "Brak konfiguracji Cloudinary",
      "deletionFailed": "Nie udało się usunąć obrazu z Cloudinary",
      "missingPublicId": "Brak publicznego ID Cloudinary"
    },
    "dictionary": {
      "SKILLS": {
        "NAME": {
          "ONE": "ONE",
          "SIX": "SIX",
          "TWO": "TWO",
          "FIVE": "FIVE",
          "FOUR": "FOUR",
          "SEVEN": "SEVEN",
          "THREE": "THREE"
        }
      },
      "LANGUAGES": {
        "NAME": {
          "bg": "bułgarski",
          "cs": "czeski",
          "da": "duński",
          "de": "niemiecki",
          "el": "grecki",
          "en": "angielski",
          "es": "hiszpański",
          "et": "estoński",
          "fi": "fiński",
          "fr": "francuski",
          "hr": "chorwacki",
          "hu": "węgierski",
          "it": "włoski",
          "lt": "litewski",
          "lv": "łotewski",
          "nl": "holenderski",
          "no": "norweski",
          "pl": "polski",
          "pt": "portugalski",
          "ro": "rumuński",
          "sk": "słowacki",
          "sl": "słoweński",
          "sv": "szwedzki"
        },
        "COUNTRY_NAME": {
          "bg": "Bułgaria",
          "cs": "Czechy",
          "da": "Dania",
          "de": "Niemcy",
          "el": "Grecja",
          "en": "Wielka Brytania",
          "es": "Hiszpania",
          "et": "Estonia",
          "fi": "Finlandia",
          "fr": "Francja",
          "hr": "Chorwacja",
          "hu": "Węgry",
          "it": "Włochy",
          "lt": "Litwa",
          "lv": "Łotwa",
          "nl": "Holandia",
          "no": "Norwegia",
          "pl": "Polska",
          "pt": "Portugalia",
          "ro": "Rumunia",
          "sk": "Słowacja",
          "sl": "Słowenia",
          "sv": "Szwecja"
        }
      },
      "CERTIFICATES": {
        "NAME": {
          "IRATA1": "IRATA L1",
          "IRATA_ONE": "IRATA L1",
          "IRATA_TWO": "IRATA L2 – Experienced Technician",
          "IRATA_THREE": "IRATA L3 – Supervisor"
        }
      }
    },
    "validation": {
      "form": {
        "required": "To pole jest wymagane.",
        "formInvalid": "Formularz jest nieprawidłowy, sprawdź wszystkie pola.",
        "positiveInteger": "Wartość musi być dodatnią liczbą całkowitą.",
        "dateRangeRequired": "Daty rozpoczęcia i zakończenia są wymagane.",
        "phoneNumberInvalid": "Nieprawidłowy format numeru telefonu.",
        "phoneNumberTooLong": "Numer telefonu jest za długi (maks. 15 cyfr).",
        "phoneNumberRequired": "Numer telefonu jest wymagany.",
        "phoneNumberTooShort": "Numer telefonu jest za krótki (min. 6 cyfr).",
        "dateRangeStartRequired": "Data rozpoczęcia jest wymagana."
      },
      "view": {
        "title": "Coś poszło nie tak!",
        "goHome": "Wróć na stronę główną",
        "reportTitle": "Pomóż nam poprawić się, zgłaszając problem"
      },
      "popup": {
        "stay": "Zostań na tej stronie",
        "title": "Wystąpił błąd",
        "goHome": "Wróć na stronę główną"
      },
      "success": "Rejestracja zakończona sukcesem!",
      "notFound": "Nie znaleziono",
      "required": "Wszystkie pola są wymagane.",
      "emailMatch": "Email i powtórzony email muszą się zgadzać.",
      "fileTooLarge": "Plik jest za duży. Maksymalny rozmiar: {{max}} MB",
      "firebaseError": "Rejestracja nie powiodła się. Spróbuj ponownie później.",
      "passwordMatch": "Hasło i powtórone hasło muszą się zgadzać.",
      "invalidFileType": "Nieprawidłowy typ pliku. Dozwolone: {{allowed}}",
      "dictionaryNotFound": "Nie znaleziono słownika"
    },
    "notification": {
      "error": {
        "notFound": "Nie można znaleźć powiadomienia o podanym ID"
      },
      "header": "Powiadomienia",
      "readAt": "Przeczytano: {{date}}",
      "sentAt": "Otrzymano: {{date}}",
      "viewProfile": "Zobacz profil {{name}}",
      "newMessageTitle": "Nowa wiadomość",
      "noNotifications": "Nie masz jeszcze żadnych powiadomień.",
      "deleteNotification": "Usuń powiadomienie",
      "deleteSuccessToast": "Powiadomienie zostało pomyślnie usunięte",
      "friendRemovedTitle": "Znajomy usunięty",
      "newInvitationTitle": "Nowe zaproszenie",
      "deleteConfirmMessage": "Czy na pewno chcesz usunąć to powiadomienie? Tej akcji nie można cofnąć.",
      "friendRemovedMessage": "Użytkownik {{name}} usunął Cię ze znajomych.",
      "newInvitationMessage": "Użytkownik {{name}} wysłał Ci zaproszenie do znajomych.",
      "acceptInvitationTitle": "Zaproszenie zaakceptowane",
      "notificationViewTitle": "Powiadomienie",
      "unreadNotificationsFew": "Masz {{count}} nieprzeczytane powiadomienia",
      "unreadNotificationsOne": "Masz {{count}} nieprzeczytane powiadomienie",
      "acceptInvitationMessage": "Użytkownik {{name}} zaakceptował Twoje zaproszenie do znajomych.",
      "unreadNotificationsMany": "Masz {{count}} nieprzeczytanych powiadomień"
    },
    "gallery": {
      "deleteTitle": "Usuń obraz",
      "deleteMessage": "Czy na pewno chcesz usunąć ten obraz? Tej akcji nie można cofnąć.",
      "title": "Galeria",
      "addImage": "Dodaj obraz"
    },
    "employeeProfile": {
      "edit": "Edytuj profil pracownika",
      "certificates": "Certyfikaty",
      "worksInIndurstryYears": "Pracuje w branży od {{years}} lat",
      "worksInIndurstryMonths": "Pracuje w branży od {{months}} miesięcy",
      "skills": "Umiejętności / doświadczenie",
      "editSkills": "Edytuj umiejętności / doświadczenie",
      "addSkill": "Dodaj element",
      "skill": "Umiejętność",
      "form": {
        "city": "Miasto",
        "email": "Email",
        "optionalinfo": "Informacje opcjonalne - pokażemy je na Twoim profilu jeśli je wypełnisz.",
        "personalData": {
          "label": "Krok 1",
          "title": "Dane osobowe"
        },
        "location": {
          "info": "*Podanie orientacyjnej lokalizacji jest wymagane do działania wyszukiwarki i ułatwia innym znalezienie Twojego profilu.",
          "label": "Krok 2",
          "title": "Lokalizacja",
          "chooseOptions": "Wybierz opcje:"
        },
        "availability": {
          "label": "Krok 3",
          "title": "Dostępność"
        },
        "certificates": {
          "label": "Krok 4",
          "title": "Certyfikaty"
        },
        "career": {
          "title": "Kariera",
          "categories": "Kategorie pracy",
          "careerStartDate": "Data rozpoczęcia kariery",
          "maxAltitude": "Maksymalna wysokość pracy (m)",
          "maxAltitudeShort": "Maksymalna wysokość",
          "readyToTravel": "Gotowość do wyjazdów"
        },
        "title": "Formularz profilu pracownika",
        "radius": "Promień",
        "address": "Adres",
        "freeText": "Szukaj...",
        "fullName": "Imię i nazwisko",
        "experience": "Doświadczenie",
        "addLanguage": "Dodaj język",
        "phoneNumber": "Numer telefonu",
        "sortOptions": {
          "title": "Sortuj według",
          "POPULARITY": "Popularność",
          "DISTANCE_ASC": "Odległość: Najbliżej",
          "CREATED_AT_ASC": "Dołączył: Najstarszy",
          "START_FROM_ASC": "Dostępność: Najdalsza",
          "CREATED_AT_DESC": "Dołączył: Najnowszy",
          "START_FROM_DESC": "Dostępność: Najbliższa"
        },
        "submitError": "Proszę poprawnie wypełnić wszystkie wymagane pola",
        "confirmTitle": "Potwierdź zapisanie profilu",
        "rangesOption": {
          "AVAILABLE_ON": {
            "msg": "Wybierz daty, w których jesteś dostępny/a do pracy.",
            "tab": "Dostępny"
          },
          "NOT_AVAILABLE_ON": {
            "msg": "Wybierz daty, w których nie jesteś dostępny/a do pracy.",
            "tab": "Niedostępny"
          }
        },
        "uploadAvatar": "Prześlij avatar",
        "confirmSubmit": "Czy na pewno chcesz zapisać profil pracownika?",
        "locationPoint": "Dokładna lokalizacja [lat lng]",
        "resetLocation": "Resetuj lokalizację",
        "submitSuccess": "Profil został zapisany pomyślnie",
        "locationOption": {
          "POSITION": {
            "msg": "Będą do Ciebie trafiać oferty na podstawie Twojej lokalizacji i odległości.",
            "tab": "Lokalizacja"
          },
          "ALL_EUROPE": {
            "msg": "Będą trafiać do Ciebie oferty z całej Europy.",
            "tab": "Europa"
          },
          "SELECTED_COUNTRIES": {
            "msg": "Będą do Ciebie trafiać ofery z wybranych krajów.",
            "tab": "Kraje"
          }
        },
        "locationCountry": "Kraj lokalizacji",
        "validationError": "Proszę wypełnić wszystkie wymagane pola w tym kroku",
        "locationCountries": "Kraje",
        "availabilityOption": {
          "ANYTIME": {
            "msg": "Szukam pracy od zaraz",
            "tab": "Od zaraz"
          },
          "FROM_DATE": {
            "msg": "Szukam pracy od dnia:",
            "tab": "Od dnia",
            "startLabel": "Data rozpoczęcia"
          },
          "DATE_RANGES": {
            "add": "Dodaj termin",
            "tab": "Terminy",
            "label": "Termin"
          }
        },
        "communicationLanguage": "Język komunikacji",
        "communicationLanguages": "Języki komunikacji",
        "certificateValidityDate": "Data ważności "
      },
      "jobs": "Zlecenia ukończone",
      "error": {
        " equired": "Dane profilu pracownika są wymagane",
        "notFound": "Nie znaleziono profilu",
        "startDate": "Brak daty rozpoczęcia",
        "uidRequired": "UID profilu pracownika jest wymagany",
        "emailRequired": "Email użytkownika jest wymagany do utworzenia profilu pracownika",
        "statusRequired": "Status profilu pracownika jest wymagany",
        "fullNameRequired": "Pełne imię i nazwisko profilu pracownika jest wymagane",
        "avatarRefRequired": "Awatar profilu pracownika jest wymagany",
        "getGeocodedLocation": "Błąd podczas pobierania lokalizacji",
        "phoneNumberRequired": "Numer telefonu profilu pracownika jest wymagany",
        "locationOptionRequired": "Opcja lokalizacji profilu pracownika jest wymagana",
        "locationRadiusRequired": "Promień lokalizacji jest wymagany dla opcji lokalizacji na odległość",
        "locationCountryRequired": "Wymagany jest co najmniej jeden kraj lokalizacji dla wybranych krajów",
        "locationPositionRequired": "Pozycja lokalizacji jest wymagana dla opcji lokalizacji na odległość",
        "residenceCountryRequired": "Kraj zamieszkania profilu pracownika jest wymagany",
        "availabilityDateRangesRequired": "Wymagany jest co najmniej jeden zakres dat dostępności",
        "communicationLanguagesRequired": "Wymagany jest co najmniej jeden język komunikacji",
        "locationCountriesMustNotBeSpecified": "Kraje lokalizacji nie mogą być określone dla opcji cała Europa",
        "availabilityDateRangeStartEndRequired": "Daty rozpoczęcia i zakończenia są wymagane dla zakresów dat dostępności"
      },
      "title": "Profil pracownika",
      "views": "Wyświetlenia",
      "create": "Utwórz profil pracownika",
      "exists": "Profil pracownika już istnieje dla tego użytkownika",
      "joined": "Dołączono:",
      "search": "Pracownicy",
      "notFound": "Nie znaleziono profilu pracownika do aktualizacji",
      "noChanges": "Brak wykrytych zmian w profilu pracownika",
      "editButton": "Edytuj profil pracownika",
      "experience": "Doświadczenie",
      "likeButton": "Polub profil",
      "profileMenu": "Menu profilu",
      "searchTitle": "Filtry wyszukiwania specjalistów",
      "availability": "Dostępność",
      "deleteButton": "Usuń profil",
      "unlikeButton": "Usuń polubienie",
      "submitSuccess": "Profil pracownika zapisany pomyślnie.",
      "activateButton": "Aktywuj profil",
      "alreadyInStatus": "Profil jest już w określonym statusie",
      "likeRemoveToast": "Usunąłeś polubienie profilu",
      "deactivateButton": "Dezaktywuj profil",
      "deleteErrorToast": "Wystąpił błąd podczas usuwania profilu",
      "likeSuccessToast": "Polubiłeś profil",
      "deleteSuccessToast": "Profil został pomyślnie usunięty",
      "cannotLikeOwnProfile": "Nie możesz polubić własnego profilu",
      "deleteConfirmMessage": "Czy na pewno chcesz usunąć ten profil pracownika? Tej akcji nie można cofnąć.",
      "activationSuccessToast": "Profil pomyślnie aktywowany",
      "deactivationSuccessToast": "Profil pomyślnie dezaktywowany"
    }
  }
}